{
  "period": "daily",
  "updated_at": "2025-04-21T05:22:27",
  "rankings": [
    {
      "title": "Mickey 17",
      "current_rank": 1,
      "previous_rank": 232,
      "rank_change": 231,
      "seeders": 8970,
      "leechers": 9555,
      "peers": 18525
    },
    {
      "title": "Mickey 17",
      "current_rank": 2,
      "previous_rank": 232,
      "rank_change": 230,
      "seeders": 8970,
      "leechers": 9555,
      "peers": 18525
    },
    {
      "title": "A Working Man",
      "current_rank": 3,
      "previous_rank": 64,
      "rank_change": 61,
      "seeders": 5158,
      "leechers": 4684,
      "peers": 9842
    },
    {
      "title": "A Working Man",
      "current_rank": 4,
      "previous_rank": 64,
      "rank_change": 60,
      "seeders": 5158,
      "leechers": 4684,
      "peers": 9842
    },
    {
      "title": "Black Bag",
      "current_rank": 5,
      "previous_rank": 184,
      "rank_change": 179,
      "seeders": 4602,
      "leechers": 2703,
      "peers": 7305
    },
    {
      "title": "Black Bag",
      "current_rank": 6,
      "previous_rank": 184,
      "rank_change": 178,
      "seeders": 4602,
      "leechers": 2703,
      "peers": 7305
    },
    {
      "title": "A Minecraft Movie",
      "current_rank": 7,
      "previous_rank": 80,
      "rank_change": 73,
      "seeders": 3990,
      "leechers": 1760,
      "peers": 5750
    },
    {
      "title": "A Minecraft Movie",
      "current_rank": 8,
      "previous_rank": 80,
      "rank_change": 72,
      "seeders": 3990,
      "leechers": 1760,
      "peers": 5750
    },
    {
      "title": "Novocaine",
      "current_rank": 9,
      "previous_rank": 32,
      "rank_change": 23,
      "seeders": 2682,
      "leechers": 2647,
      "peers": 5329
    },
    {
      "title": "Novocaine",
      "current_rank": 10,
      "previous_rank": 32,
      "rank_change": 22,
      "seeders": 2682,
      "leechers": 2647,
      "peers": 5329
    },
    {
      "title": "The Monkey",
      "current_rank": 11,
      "previous_rank": 56,
      "rank_change": 45,
      "seeders": 2662,
      "leechers": 1201,
      "peers": 3863
    },
    {
      "title": "The Monkey",
      "current_rank": 12,
      "previous_rank": 56,
      "rank_change": 44,
      "seeders": 2662,
      "leechers": 1201,
      "peers": 3863
    },
    {
      "title": "In the Lost Lands",
      "current_rank": 13,
      "previous_rank": 48,
      "rank_change": 35,
      "seeders": 2845,
      "leechers": 919,
      "peers": 3764
    },
    {
      "title": "In the Lost Lands",
      "current_rank": 14,
      "previous_rank": 48,
      "rank_change": 34,
      "seeders": 2845,
      "leechers": 919,
      "peers": 3764
    },
    {
      "title": "Sinners",
      "current_rank": 15,
      "previous_rank": null,
      "rank_change": "new",
      "seeders": 1163,
      "leechers": 2419,
      "peers": 3582
    },
    {
      "title": "Sinners",
      "current_rank": 16,
      "previous_rank": null,
      "rank_change": "new",
      "seeders": 1163,
      "leechers": 2419,
      "peers": 3582
    },
    {
      "title": "A Working Man",
      "current_rank": 17,
      "previous_rank": 64,
      "rank_change": 47,
      "seeders": 1545,
      "leechers": 1063,
      "peers": 2608
    },
    {
      "title": "A Working Man",
      "current_rank": 18,
      "previous_rank": 64,
      "rank_change": 46,
      "seeders": 1545,
      "leechers": 1063,
      "peers": 2608
    },
    {
      "title": "A Minecraft Movie",
      "current_rank": 19,
      "previous_rank": 80,
      "rank_change": 61,
      "seeders": 405,
      "leechers": 1630,
      "peers": 2035
    },
    {
      "title": "A Minecraft Movie",
      "current_rank": 20,
      "previous_rank": 80,
      "rank_change": 60,
      "seeders": 405,
      "leechers": 1630,
      "peers": 2035
    }
  ]
}